topsis/__init__.py
topsis/__main__.py
topsis_bhavya_102103345-1.0.2.dist-info/LICENSE
topsis_bhavya_102103345-1.0.2.dist-info/METADATA
topsis_bhavya_102103345-1.0.2.dist-info/WHEEL
topsis_bhavya_102103345-1.0.2.dist-info/entry_points.txt
topsis_bhavya_102103345-1.0.2.dist-info/top_level.txt
topsis_bhavya_102103345-1.0.2.dist-info/RECORD
